alchemy_store/__init__.py
alchemy_store/custom_types.py
alchemy_store/message_store.py
arame/__init__.py
arame/gateway.py
arame/messaging.py
brightside/__init__.py
brightside/channels.py
brightside/command_processor.py
brightside/connection.py
brightside/dispatch.py
brightside/exceptions.py
brightside/handler.py
brightside/log_handler.py
brightside/message_factory.py
brightside/message_pump.py
brightside/messaging.py
brightside/registry.py
brightside-0.6.13.dist-info/LICENSE
brightside-0.6.13.dist-info/METADATA
brightside-0.6.13.dist-info/WHEEL
brightside-0.6.13.dist-info/top_level.txt
brightside-0.6.13.dist-info/RECORD
