Metadata-Version: 2.1
Name: brightside
Version: 0.6.13
Summary: Provides a command dispatcher and task queue to support CQRS and microservices
Home-page: https://github.com/BrighterCommand/Brightside
Author: Ian Cooper
Author-email: ian_hammond_cooper@yahoo.co.uk
License: MIT
Keywords: brightside,messaging,command,dispatcher,invoker,CQRS,microservices
Platform: UNKNOWN
Classifier: License :: OSI Approved :: MIT License
Classifier: Programming Language :: Python
Classifier: Programming Language :: Python :: 3
Classifier: Programming Language :: Python :: 3.6
Classifier: Programming Language :: Python :: Implementation :: CPython
Classifier: Programming Language :: Python :: Implementation :: PyPy
Classifier: Development Status :: 2 - Pre-Alpha
Classifier: Intended Audience :: Developers
Classifier: Intended Audience :: Information Technology
Classifier: Natural Language :: English
Classifier: Operating System :: OS Independent
Classifier: Topic :: System :: Monitoring
Classifier: Topic :: System :: Distributed Computing
Requires-Python: >=3.6.0
Requires-Dist: kombu
Requires-Dist: sqlalchemy
